invenio_db/__init__.py
invenio_db/cli.py
invenio_db/ext.py
invenio_db/proxies.py
invenio_db/shared.py
invenio_db/uow.py
invenio_db/utils.py
invenio_db/alembic/35c1075e6360_force_naming_convention.py
invenio_db/alembic/96e796392533_create_database_migrations.py
invenio_db/alembic/dbdbc1b19cf2_create_transaction_table.py
invenio_db/alembic/script.py.mako
invenio_db-2.2.1.dist-info/licenses/AUTHORS.rst
invenio_db-2.2.1.dist-info/licenses/LICENSE
invenio_db-2.2.1.dist-info/METADATA
invenio_db-2.2.1.dist-info/WHEEL
invenio_db-2.2.1.dist-info/entry_points.txt
invenio_db-2.2.1.dist-info/top_level.txt
invenio_db-2.2.1.dist-info/RECORD
