Metadata-Version: 2.4
Name: invenio-db
Version: 2.2.1
Summary: Database management for Invenio.
Home-page: https://github.com/inveniosoftware/invenio-db
Author: CERN
Author-email: info@inveniosoftware.org
License: MIT
Keywords: invenio database
Platform: any
Classifier: Development Status :: 5 - Production/Stable
Requires-Python: >=3.7
License-File: LICENSE
License-File: AUTHORS.rst
Requires-Dist: alembic>=1.10.0
Requires-Dist: Flask-Alembic<3.2.0,>=3.0.0
Requires-Dist: Flask-SQLAlchemy>=3.0
Requires-Dist: invenio-base<3.0.0,>=2.3.0
Requires-Dist: SQLAlchemy-Continuum<1.6.0,>=1.3.12
Requires-Dist: SQLAlchemy-Utils<0.42.0,>=0.33.1
Requires-Dist: SQLAlchemy[asyncio]>=2.0.0
Provides-Extra: tests
Requires-Dist: six>=1.0.0; extra == "tests"
Requires-Dist: pytest-black-ng>=0.4.0; extra == "tests"
Requires-Dist: cryptography>=2.1.4; extra == "tests"
Requires-Dist: pytest-invenio<4.0.0,>=3.0.0; extra == "tests"
Requires-Dist: Sphinx>=4.5.0; extra == "tests"
Provides-Extra: mysql
Requires-Dist: pymysql>=0.10.1; extra == "mysql"
Provides-Extra: postgresql
Requires-Dist: psycopg2-binary>=2.8.6; extra == "postgresql"
Provides-Extra: versioning
Dynamic: license-file
